[{"run_index": 0, "energy": -194.0, "vars": [1, 0, 0, 0, 1, 0, 1, 0, 0, 1, 0, 0, 0, 0, 1, 0, 0, 0], "opt_runtime": 351.8151230812073}, {"run_index": 1, "energy": -195.5, "vars": [0, 1, 0, 0, 0, 1, 0, 0, 1, 0, 1, 0, 0, 0, 0, 0, 1, 0], "opt_runtime": 351.303870677948}, {"run_index": 2, "energy": -196.0, "vars": [0, 1, 0, 0, 0, 1, 0, 0, 1, 0, 1, 0, 0, 0, 0, 1, 0, 0], "opt_runtime": 390.3076603412628}, {"run_index": 3, "energy": -195.5, "vars": [1, 0, 0, 0, 0, 1, 0, 0, 0, 0, 0, 1, 1, 0, 0, 0, 0, 1], "opt_runtime": 374.75711584091187}, {"run_index": 4, "energy": -196.5, "vars": [0, 0, 1, 0, 0, 1, 0, 0, 1, 1, 0, 0, 0, 0, 0, 1, 0, 0], "opt_runtime": 350.8734481334686}, {"run_index": 5, "energy": -196.5, "vars": [0, 0, 1, 1, 0, 0, 0, 0, 1, 1, 0, 0, 0, 0, 0, 1, 0, 0], "opt_runtime": 406.3917520046234}, {"run_index": 6, "energy": -197.5, "vars": [1, 0, 0, 0, 1, 0, 1, 0, 0, 1, 0, 0, 0, 0, 0, 1, 0, 0], "opt_runtime": 327.55410957336426}, {"run_index": 7, "energy": -194.0, "vars": [1, 0, 0, 0, 0, 0, 1, 0, 0, 0, 1, 0, 1, 0, 0, 0, 1, 0], "opt_runtime": 320.2378306388855}, {"run_index": 8, "energy": -191.5, "vars": [1, 0, 0, 0, 0, 1, 0, 0, 1, 0, 0, 1, 0, 0, 1, 0, 1, 0], "opt_runtime": 271.4891152381897}, {"run_index": 9, "energy": -197.5, "vars": [1, 0, 0, 0, 1, 0, 1, 0, 0, 1, 0, 0, 0, 0, 0, 1, 0, 0], "opt_runtime": 328.30210304260254}]